yotsuba/__init__.py
yotsuba/ja.py
yotsuba/version.py
yotsuba/yotsuba.cp37-win_amd64.pyd
yotsuba_python-0.1.3.dist-info/METADATA
yotsuba_python-0.1.3.dist-info/WHEEL
yotsuba_python-0.1.3.dist-info/top_level.txt
yotsuba_python-0.1.3.dist-info/RECORD
