Metadata-Version: 2.1
Name: yotsuba-python
Version: 0.1.3
Summary: a
Home-page: https://github.com/yutayamazaki/yotsuba
Author: Yuta Yamazaki
Author-email: yu.yamazakii@gmail.com
Maintainer: Yuta Yamazaki
Maintainer-email: yu.yamazakii@gmail.com
License: MIT
Keywords: nlp python rust
Platform: UNKNOWN
